Workbook

Sheet Instructions
A1: ALPHA POD — Valuation Review Template
A3: SETUP (one-time)
A4: 1. In Excel: Data → Get Data → From Text/CSV
A5: 2. Navigate to: ai-fund/data/valuations/latest.csv
A6: 3. Click 'Load To...' → select 'Table' and 'Existing worksheet'
A7: 4. Place at cell A1 on the 'Data' sheet
A8: 5. Done! The Data sheet now auto-refreshes from Python output
A10: DAILY WORKFLOW
A11: 1. Run: python -m src.valuation.batch_runner
A12: 2. Open this workbook → Data → Refresh All (Ctrl+Alt+F5)
A13: 3. Review the Dashboard tab — sorted by upside
A14: 4. To adjust assumptions: go to Overrides tab, enter your values
... A21: • Overrides persist across refreshes — Python never touches this file

Sheet Dashboard
A1: ALPHA POD — Valuation Dashboard
A2: =TEXT(NOW(), "YYYY-MM-DD HH:MM")
A4: QUICK STATS
A5: Total Valued: | B5: =COUNTA(Data!A:A)-1
A6: Avg Upside (base): | B6: =AVERAGE(Data!AB:AB)
A7: Median WACC: | B7: =MEDIAN(Data!R:R)
A8: Names > 20% upside: | B8: =COUNTIF(Data!AB:AB,">20")
A9: Names > 50% upside: | B9: =COUNTIF(Data!AB:AB,">50")
A12: SECTOR BREAKDOWN
A13: Sector | B13: Count | C13: Avg Upside
A14: Technology | B14: =COUNTIF(Data!C:C,"Technology") | C14: =IFERROR(AVERAGEIF(Data!C:C,"Technology",Data!AB:AB),"-")
A15: Healthcare | B15: =COUNTIF(Data!C:C,"Healthcare") | C15: =IFERROR(AVERAGEIF(Data!C:C,"Healthcare",Data!AB:AB),"-")
A16: Industrials | B16: =COUNTIF(Data!C:C,"Industrials") | C16: =IFERROR(AVERAGEIF(Data!C:C,"Industrials",Data!AB:AB),"-")
A17: Consumer Cyclical | B17: =COUNTIF(Data!C:C,"Consumer Cyclical") | C17: =IFERROR(AVERAGEIF(Data!C:C,"Consumer Cyclical",Data!AB:AB),"-")
A18: Consumer Defensive | B18: =COUNTIF(Data!C:C,"Consumer Defensive") | C18: =IFERROR(AVERAGEIF(Data!C:C,"Consumer Defensive",Data!AB:AB),"-")
A19: Energy | B19: =COUNTIF(Data!C:C,"Energy") | C19: =IFERROR(AVERAGEIF(Data!C:C,"Energy",Data!AB:AB),"-")
A20: Basic Materials | B20: =COUNTIF(Data!C:C,"Basic Materials") | C20: =IFERROR(AVERAGEIF(Data!C:C,"Basic Materials",Data!AB:AB),"-")
A21: Communication Services | B21: =COUNTIF(Data!C:C,"Communication Services") | C21: =IFERROR(AVERAGEIF(Data!C:C,"Communication Services",Data!AB:AB),"-")
A24: HOW TO USE
A25: 1. Run batch_runner → Ctrl+Alt+F5 to refresh
A26: 2. Review this Dashboard for overview
A27: 3. Overrides tab to adjust assumptions for specific tickers
A28: 4. Model tab shows merged output (Python default + your overrides)

Sheet Data
A1: ticker | B1: company_name | C1: sector | D1: industry | E1: price | F1: market_cap_mm | G1: ev_mm | H1: pe_trailing | I1: pe_forward | J1: ev_ebitda | K1: revenue_mm | L1: op_margin | M1: profit_margin | N1: rev_growth | O1: fcf_mm | P1: net_debt_mm | Q1: beta_raw | R1: wacc | S1: cost_of_equity | T1: beta_relevered | U1: beta_unlevered | V1: size_premium | W1: equity_weight | X1: peers_used | Y1: iv_bear | Z1: iv_base | AA1: iv_bull | AB1: upside_base_pct | AC1: upside_bear_pct | AD1: upside_bull_pct | AE1: margin_of_safety | AF1: growth_near | AG1: growth_mid | AH1: ebit_margin_used | AI1: exit_multiple_used | AJ1: tv_pct_of_ev | AK1: analyst_target | AL1: analyst_recommendation | AM1: num_analysts
A2: ← Power Query loads data here. Data → Refresh All to update.

Sheet Overrides
A1: Ticker | B1: growth_near (%) | C1: growth_mid (%) | D1: ebit_margin (%) | E1: wacc (%) | F1: exit_multiple (x) | G1: Reason
A2: HALO | B2: 12 | C2: 8 | G2: Cap growth — drug patent cliff in 2030
A3: LYFT | F3: 25 | G3: SaaS-like unit economics justify higher multiple

Sheet Model
A1: Ticker | B1: Company | C1: Sector | D1: Price | E1: Growth Near (%) | F1: Growth Mid (%) | G1: EBIT Margin (%) | H1: WACC (%) | I1: Exit Multiple (x) | J1: IV Bear | K1: IV Base | L1: IV Bull | M1: Upside Base (%) | N1: Margin of Safety (%) | O1: Source
A2: =Data!A2 | B2: =Data!B2 | C2: =Data!C2 | D2: =Data!E2 | E2: =IFERROR(VLOOKUP(A2,Overrides!A:G,2,0), Data!AF2) | F2: =IFERROR(VLOOKUP(A2,Overrides!A:G,3,0), Data!AG2) | G2: =IFERROR(VLOOKUP(A2,Overrides!A:G,4,0), Data!AH2) | H2: =IFERROR(VLOOKUP(A2,Overrides!A:G,5,0), Data!R2) | I2: =IFERROR(VLOOKUP(A2,Overrides!A:G,6,0), Data!AI2) | J2: =Data!Y2 | K2: =Data!Z2 | L2: =Data!AA2 | M2: =Data!AB2 | N2: =Data!AE2 | O2: =IF(ISNA(VLOOKUP(A2,Overrides!A:G,2,0)),"Default","Override")
A3: ← Fill formulas referencing Data + Overrides sheets
A4: FORMULA GUIDE: Row 2 has template formulas. After Power Query loads data into the Data sheet, adjust column references to match, then copy row 2 down for all tickers.
