Workbook
Name Ccy: Input!$B$7
Name Conv: Input!$B$8
Name Date: Input!$B$6
Name InputTicker: Input!$B$2
Name IQ_CH: 110000
Name IQ_CQ: 5000
Name IQ_CY: 10000
Name IQ_DAILY: 500000
Name IQ_FH: 100000
Name IQ_FQ: 500
Name IQ_FY: 1000
Name IQ_LTM: 2000
Name IQ_MONTH: 15000
Name IQ_NTM: 6000
Name IQ_WEEK: 50000
Name IQ_YTD: 3000
Name Languages: OFFSET(#REF!,,,#REF!)
Name SPWS_WBID: "0D145571-4AA7-4C6E-B8EB-4DF0FED2B8BC"

Sheet Input_Raw
A1: Name | B1: Value
A2: ticker | B2: NASDAQ:CALM
A3: date_year | B3: 2026
A4: date_month | B4: 3
A5: date_day | B5: 29
A6: currency | B6: USD

Sheet Input
A1: =Input_Raw!A1 -> Name | B1: =Input_Raw!B1 -> Value
A2: =Input_Raw!A2 -> ticker | B2: =Input_Raw!B2 -> NASDAQ:CALM | D2: 990 | E2: =D2+1 -> 991 | F2: =E2+1 -> 992 | G2: =F2+1 -> 993 | H2: =G2+1 -> 994 | I2: =H2+1 -> 995 | J2: =I2+1 -> 996 | K2: =J2+1 -> 997 | L2: =K2+1 -> 998 | ... N2: =M2+1 -> 1000 | O2: 2000
A3: =Input_Raw!A3 -> date_year | B3: =Input_Raw!B3 -> 2026
A4: =Input_Raw!A4 -> date_month | B4: =Input_Raw!B4 -> 3
A5: =Input_Raw!A5 -> date_day | B5: =Input_Raw!B5 -> 29
A6: date | B6: =DATE(B3,B4,B5) -> 46110
A7: =Input_Raw!A6 -> currency | B7: =Input_Raw!B6 -> USD
A8: conversion | B8: H

Sheet _CIQHiddenCacheSheet
